dscan/__init__.py
dscan/__main__.py
dscan/client.py
dscan/out.py
dscan/server.py
dscan/data/__init__.py
dscan/data/agent.conf
dscan/data/dscan.conf
dscan/models/__init__.py
dscan/models/parsers.py
dscan/models/scanner.py
dscan/models/structures.py
dscan_4e656f-0.1.7.data/scripts/dscan
dscan_4e656f-0.1.7.dist-info/licenses/LICENSE.txt
dscan_4e656f-0.1.7.dist-info/METADATA
dscan_4e656f-0.1.7.dist-info/WHEEL
dscan_4e656f-0.1.7.dist-info/top_level.txt
dscan_4e656f-0.1.7.dist-info/RECORD
