Metadata-Version: 2.4
Name: dscan-4E656F
Version: 0.1.7
Summary: Wrapper around nmap allow nmap scans to be distributed with resume, and address optimization.
Home-page: https://github.com/0x4E0x650x6F/dscan
Author: 0x4E0x650x6F
Author-email: tiago.alexand@gmail.com
License: GPL version 3
Classifier: License :: OSI Approved :: GNU General Public License v3 (GPLv3)
Classifier: Development Status :: 5 - Production/Stable
Classifier: Environment :: Console
Classifier: Programming Language :: Python :: 3.6
Classifier: Programming Language :: Python :: 3.7
Classifier: Programming Language :: Python :: 3.8
Classifier: Programming Language :: Python :: 3.12
Classifier: Topic :: System :: Networking
Requires-Python: >=3.6
License-File: LICENSE.txt
Requires-Dist: python-libnmap
Dynamic: author
Dynamic: author-email
Dynamic: classifier
Dynamic: description
Dynamic: description-content-type
Dynamic: home-page
Dynamic: license
Dynamic: license-file
Dynamic: requires-dist
Dynamic: requires-python
Dynamic: summary
